midi_clip/__init__.py
midi_clip/midi_clip.py
midi_clip/midi_duration.py
midi_clip-0.10.dist-info/LICENSE.md
midi_clip-0.10.dist-info/METADATA
midi_clip-0.10.dist-info/WHEEL
midi_clip-0.10.dist-info/top_level.txt
midi_clip-0.10.dist-info/RECORD
