Metadata-Version: 2.1
Name: midi-clip
Version: 0.10
Summary: A python package for midi clip.
Home-page: https://github.com/kyaryunha/midi-clip
Author: kyaryunha
Author-email: kyaryunha@gmail.com
License: ISC
Keywords: midi MIDI mir music audio sound midi-clip python python3
License-File: LICENSE.md
Requires-Dist: mido
